{
  "refreshedAt": "2025-11-30T07:46:45.513Z",
  "count": 154,
  "freshCount": 113,
  "coreCount": 46,
  "symbols": [
    "ANPA",
    "ECDA",
    "CLSD",
    "IMPP",
    "TLRY",
    "ZYXI",
    "SGBX",
    "LEDS",
    "XTKG",
    "ZCAR",
    "QNTM",
    "AGCC",
    "ISPC",
    "LINK",
    "ZSL",
    "CETY",
    "BUUU",
    "ATXI",
    "NAMM",
    "EQ",
    "SYBX",
    "IPEXR",
    "NTCL",
    "DDC",
    "SONN",
    "ARBKL",
    "AEHL",
    "ATLN",
    "NEPH",
    "MRNO",
    "CYPH",
    "MENS",
    "IRWD",
    "GRNQ",
    "AIIO",
    "GPUS",
    "LPTX",
    "SPRB",
    "SOXS",
    "AMZE",
    "HBI",
    "BEAT",
    "KTTA",
    "INTC",
    "BYND",
    "BITF",
    "SOXL",
    "OPEN",
    "BMNR",
    "CLSK",
    "TSLL",
    "PLUG",
    "ASST",
    "BIYA",
    "AAL",
    "SNAP",
    "CIFR",
    "TQQQ",
    "ONMD",
    "ONDS",
    "WULF",
    "NIO",
    "TZA",
    "F",
    "BURU",
    "VALE",
    "SOFI",
    "BTBT",
    "DEFT",
    "ADTX",
    "BTG",
    "ACHR",
    "MARA",
    "INHD",
    "SMX",
    "VEEE",
    "WBUY",
    "VRCA",
    "CNTM",
    "APUS",
    "NWGL",
    "SRL",
    "NXTT",
    "FBYD",
    "BNC",
    "EURKR",
    "PAPL",
    "TMC",
    "LNZA",
    "GEOS",
    "LOBO",
    "ONCO",
    "WOK",
    "SVRA",
    "YHC",
    "JXG",
    "JFBR",
    "OWLS",
    "ATMV",
    "GWAV",
    "GFAI",
    "KULR",
    "YCBD",
    "PAVS",
    "ANL",
    "EXK",
    "AREB",
    "PRPH",
    "PTN",
    "COOT",
    "SYNX",
    "OFAL",
    "GAUZ",
    "MULN",
    "WKHS",
    "GOEV",
    "NKLA",
    "LCID",
    "RIVN",
    "FFIE",
    "FSR",
    "LAZR",
    "QS",
    "FCEL",
    "BLNK",
    "CHPT",
    "EVGO",
    "RIDE",
    "ARVL",
    "PTRA",
    "XL",
    "TTCF",
    "OTLY",
    "PRTY",
    "CGC",
    "ACB",
    "SNDL",
    "HEXO",
    "GRWG",
    "BBBY",
    "GME",
    "AMC",
    "CLOV",
    "WISH",
    "HOOD",
    "SPCE",
    "RKLB",
    "ASTR",
    "RDW",
    "ASTS",
    "UPST",
    "AFRM",
    "LMND",
    "ROOT"
  ],
  "freshDetails": [
    {
      "symbol": "ANPA",
      "companyName": "Rich Sparkle Holdings Limited Ordinary Shares",
      "price": 16.31,
      "change": -10.24,
      "changesPercentage": -38.56874,
      "exchange": "NASDAQ",
      "source": "loser"
    },
    {
      "symbol": "ECDA",
      "companyName": "ECD Automotive Design, Inc.",
      "price": 0.3795,
      "change": -0.1561,
      "changesPercentage": -29.14488,
      "exchange": "NASDAQ",
      "source": "loser"
    },
    {
      "symbol": "CLSD",
      "companyName": "Clearside Biomedical, Inc.",
      "price": 0.41,
      "change": -0.1513,
      "changesPercentage": -26.95528,
      "exchange": "NASDAQ",
      "source": "loser"
    },
    {
      "symbol": "IMPP",
      "companyName": "Imperial Petroleum Inc.",
      "price": 4.69,
      "change": -1.31,
      "changesPercentage": -21.83333,
      "exchange": "NASDAQ",
      "source": "loser"
    },
    {
      "symbol": "TLRY",
      "companyName": "Tilray Brands, Inc.",
      "price": 0.8155,
      "change": -0.2145,
      "changesPercentage": -20.82524,
      "exchange": "NASDAQ",
      "source": "loser"
    },
    {
      "symbol": "ZYXI",
      "companyName": "Zynex, Inc.",
      "price": 1.26,
      "change": -0.33,
      "changesPercentage": -20.75472,
      "exchange": "NASDAQ",
      "source": "loser"
    },
    {
      "symbol": "SGBX",
      "companyName": "Safe & Green Holdings Corp.",
      "price": 3.26,
      "change": -0.64,
      "changesPercentage": -16.41026,
      "exchange": "NASDAQ",
      "source": "loser"
    },
    {
      "symbol": "LEDS",
      "companyName": "SemiLEDs Corporation",
      "price": 2.02,
      "change": -0.386,
      "changesPercentage": -16.04323,
      "exchange": "NASDAQ",
      "source": "loser"
    },
    {
      "symbol": "XTKG",
      "companyName": "X3 Holdings Co Ltd.",
      "price": 1.67,
      "change": -0.31,
      "changesPercentage": -15.65657,
      "exchange": "NASDAQ",
      "source": "loser"
    },
    {
      "symbol": "ZCAR",
      "companyName": "Zoomcar Holdings, Inc.",
      "price": 0.22,
      "change": -0.04,
      "changesPercentage": -15.38462,
      "exchange": "NASDAQ",
      "source": "loser"
    },
    {
      "symbol": "QNTM",
      "companyName": "Quantum BioPharma Ltd.",
      "price": 9.7,
      "change": -1.71,
      "changesPercentage": -14.98685,
      "exchange": "NASDAQ",
      "source": "loser"
    },
    {
      "symbol": "AGCC",
      "companyName": "Agencia Comercial Spirits Ltd",
      "price": 6.1,
      "change": -1.07,
      "changesPercentage": -14.92329,
      "exchange": "NASDAQ",
      "source": "loser"
    },
    {
      "symbol": "ISPC",
      "companyName": "iSpecimen Inc.",
      "price": 0.4201,
      "change": -0.0634,
      "changesPercentage": -13.11272,
      "exchange": "NASDAQ",
      "source": "loser"
    },
    {
      "symbol": "LINK",
      "companyName": "Interlink Electronics, Inc.",
      "price": 3.62,
      "change": -0.53,
      "changesPercentage": -12.77108,
      "exchange": "NASDAQ",
      "source": "loser"
    },
    {
      "symbol": "ZSL",
      "companyName": "ProShares UltraShort Silver",
      "price": 9.5,
      "change": -1.38,
      "changesPercentage": -12.68382,
      "exchange": "AMEX",
      "source": "loser"
    },
    {
      "symbol": "CETY",
      "companyName": "Clean Energy Technologies, Inc.",
      "price": 1.81,
      "change": -0.25,
      "changesPercentage": -12.13592,
      "exchange": "NASDAQ",
      "source": "loser"
    },
    {
      "symbol": "BUUU",
      "companyName": "BUUU Group Limited Class A Ordinary Share",
      "price": 7.05,
      "change": -0.97,
      "changesPercentage": -12.09476,
      "exchange": "NASDAQ",
      "source": "loser"
    },
    {
      "symbol": "ATXI",
      "companyName": "Avenue Therapeutics, Inc.",
      "price": 0.76455,
      "change": -0.10435,
      "changesPercentage": -12.00944,
      "exchange": "NASDAQ",
      "source": "loser"
    },
    {
      "symbol": "NAMM",
      "companyName": "Namib Minerals Ordinary Shares",
      "price": 1.33,
      "change": -0.18,
      "changesPercentage": -11.92053,
      "exchange": "NASDAQ",
      "source": "loser"
    },
    {
      "symbol": "EQ",
      "companyName": "Equillium, Inc.",
      "price": 0.9024,
      "change": -0.1176,
      "changesPercentage": -11.52941,
      "exchange": "NASDAQ",
      "source": "loser"
    },
    {
      "symbol": "SYBX",
      "companyName": "Synlogic, Inc.",
      "price": 1.46,
      "change": -0.19,
      "changesPercentage": -11.51515,
      "exchange": "NASDAQ",
      "source": "loser"
    },
    {
      "symbol": "IPEXR",
      "companyName": "Inflection Point Acquisition Corp. V",
      "price": 0.85,
      "change": -0.11,
      "changesPercentage": -11.45833,
      "exchange": "NASDAQ",
      "source": "loser"
    },
    {
      "symbol": "NTCL",
      "companyName": "NetClass Technology Inc",
      "price": 1.07,
      "change": -0.1294,
      "changesPercentage": -10.78873,
      "exchange": "NASDAQ",
      "source": "loser"
    },
    {
      "symbol": "DDC",
      "companyName": "DDC Enterprise Limited",
      "price": 3.26,
      "change": -0.39,
      "changesPercentage": -10.68493,
      "exchange": "AMEX",
      "source": "loser"
    },
    {
      "symbol": "SONN",
      "companyName": "Sonnet BioTherapeutics Holdings, Inc.",
      "price": 3.72,
      "change": -0.435,
      "changesPercentage": -10.46931,
      "exchange": "NASDAQ",
      "source": "loser"
    },
    {
      "symbol": "ARBKL",
      "companyName": "Argo Blockchain plc 8.75% Senior Notes due 2026",
      "price": 1.12,
      "change": -0.13,
      "changesPercentage": -10.4,
      "exchange": "NASDAQ",
      "source": "loser"
    },
    {
      "symbol": "AEHL",
      "companyName": "Antelope Enterprise Holdings Limited",
      "price": 3.11,
      "change": -0.36,
      "changesPercentage": -10.37464,
      "exchange": "NASDAQ",
      "source": "loser"
    },
    {
      "symbol": "ATLN",
      "companyName": "Atlantic International Corp.",
      "price": 2.045,
      "change": -0.225,
      "changesPercentage": -9.91189,
      "exchange": "NASDAQ",
      "source": "loser"
    },
    {
      "symbol": "NEPH",
      "companyName": "Nephros, Inc.",
      "price": 4.88,
      "change": -0.53,
      "changesPercentage": -9.79667,
      "exchange": "NASDAQ",
      "source": "loser"
    },
    {
      "symbol": "MRNO",
      "companyName": "Murano Global Investments PLC Ordinary Shares",
      "price": 1.75,
      "change": -0.19,
      "changesPercentage": -9.79381,
      "exchange": "NASDAQ",
      "source": "loser"
    },
    {
      "symbol": "CYPH",
      "companyName": "Cypherpunk Technologies Inc.",
      "price": 1.53,
      "change": -0.16,
      "changesPercentage": -9.46746,
      "exchange": "NASDAQ",
      "source": "loser"
    },
    {
      "symbol": "MENS",
      "companyName": "Jyong Biotech Ltd. Ordinary Shares",
      "price": 27.2,
      "change": -2.81,
      "changesPercentage": -9.36355,
      "exchange": "NASDAQ",
      "source": "loser"
    },
    {
      "symbol": "IRWD",
      "companyName": "Ironwood Pharmaceuticals, Inc.",
      "price": 3.5,
      "change": -0.36,
      "changesPercentage": -9.32642,
      "exchange": "NASDAQ",
      "source": "loser"
    },
    {
      "symbol": "GRNQ",
      "companyName": "Greenpro Capital Corp.",
      "price": 1.56,
      "change": -0.16,
      "changesPercentage": -9.30233,
      "exchange": "NASDAQ",
      "source": "loser"
    },
    {
      "symbol": "AIIO",
      "companyName": "Robo.ai Inc.",
      "price": 0.6984,
      "change": -0.0716,
      "changesPercentage": -9.2987,
      "exchange": "NASDAQ",
      "source": "loser"
    },
    {
      "symbol": "GPUS",
      "companyName": "Hyperscale Data, Inc.",
      "price": 0.3022,
      "change": -0.0308,
      "changesPercentage": -9.24925,
      "exchange": "NYSE",
      "source": "loser"
    },
    {
      "symbol": "LPTX",
      "companyName": "Leap Therapeutics, Inc.",
      "price": 1.535,
      "change": -0.155,
      "changesPercentage": -9.1716,
      "exchange": "NASDAQ",
      "source": "loser"
    },
    {
      "symbol": "SPRB",
      "companyName": "Spruce Biosciences, Inc.",
      "price": 100,
      "change": -10,
      "changesPercentage": -9.09091,
      "exchange": "NASDAQ",
      "source": "loser"
    },
    {
      "symbol": "SOXS",
      "companyName": "Direxion Daily Semiconductor Bear 3X Shares",
      "price": 3.435,
      "change": -0.195,
      "changesPercentage": -5.3719,
      "exchange": "AMEX",
      "source": "active"
    },
    {
      "symbol": "AMZE",
      "companyName": "Amaze Holdings, Inc.",
      "price": 0.48,
      "change": 0.084,
      "changesPercentage": 21.21212,
      "exchange": "NYSE",
      "source": "active"
    },
    {
      "symbol": "HBI",
      "companyName": "Hanesbrands Inc.",
      "price": 6.47,
      "change": -0.12,
      "changesPercentage": -1.82094,
      "exchange": "NYSE",
      "source": "active"
    },
    {
      "symbol": "BEAT",
      "companyName": "HeartBeam, Inc.",
      "price": 0.75,
      "change": 0.1463,
      "changesPercentage": 24.23389,
      "exchange": "NASDAQ",
      "source": "active"
    },
    {
      "symbol": "KTTA",
      "companyName": "Pasithea Therapeutics Corp.",
      "price": 1.47,
      "change": 0.41,
      "changesPercentage": 38.67925,
      "exchange": "NASDAQ",
      "source": "active"
    },
    {
      "symbol": "INTC",
      "companyName": "Intel Corporation",
      "price": 40.56,
      "change": 3.78,
      "changesPercentage": 10.27732,
      "exchange": "NASDAQ",
      "source": "active"
    },
    {
      "symbol": "BYND",
      "companyName": "Beyond Meat, Inc.",
      "price": 0.9809,
      "change": -0.0391,
      "changesPercentage": -3.83333,
      "exchange": "NASDAQ",
      "source": "active"
    },
    {
      "symbol": "BITF",
      "companyName": "Bitfarms Ltd.",
      "price": 3.48,
      "change": 0.38,
      "changesPercentage": 12.25806,
      "exchange": "NASDAQ",
      "source": "active"
    },
    {
      "symbol": "SOXL",
      "companyName": "Direxion Daily Semiconductor Bull 3X Shares",
      "price": 41.27,
      "change": 2.08,
      "changesPercentage": 5.30748,
      "exchange": "AMEX",
      "source": "active"
    },
    {
      "symbol": "OPEN",
      "companyName": "Opendoor Technologies Inc.",
      "price": 7.66,
      "change": -0.12,
      "changesPercentage": -1.54242,
      "exchange": "NASDAQ",
      "source": "active"
    },
    {
      "symbol": "BMNR",
      "companyName": "Bitmine Immersion Technologies, Inc.",
      "price": 33.12,
      "change": 1.38,
      "changesPercentage": 4.34783,
      "exchange": "AMEX",
      "source": "active"
    },
    {
      "symbol": "CLSK",
      "companyName": "CleanSpark, Inc.",
      "price": 15.21,
      "change": 1.76,
      "changesPercentage": 13.0855,
      "exchange": "NASDAQ",
      "source": "active"
    },
    {
      "symbol": "TSLL",
      "companyName": "Direxion Daily TSLA Bull 2X Shares",
      "price": 18.485,
      "change": 0.255,
      "changesPercentage": 1.39879,
      "exchange": "NASDAQ",
      "source": "active"
    },
    {
      "symbol": "PLUG",
      "companyName": "Plug Power Inc.",
      "price": 2.025,
      "change": 0.045,
      "changesPercentage": 2.27273,
      "exchange": "NASDAQ",
      "source": "active"
    },
    {
      "symbol": "ASST",
      "companyName": "Strive, Inc.",
      "price": 1.12,
      "change": -0.01,
      "changesPercentage": -0.88496,
      "exchange": "NASDAQ",
      "source": "active"
    },
    {
      "symbol": "BIYA",
      "companyName": "Baiya International Group Inc. Ordinary Shares",
      "price": 0.2951,
      "change": 0.043,
      "changesPercentage": 17.05672,
      "exchange": "NASDAQ",
      "source": "active"
    },
    {
      "symbol": "AAL",
      "companyName": "American Airlines Group Inc.",
      "price": 14.045,
      "change": 0.115,
      "changesPercentage": 0.82556,
      "exchange": "NASDAQ",
      "source": "active"
    },
    {
      "symbol": "SNAP",
      "companyName": "Snap Inc.",
      "price": 7.655,
      "change": 0.045,
      "changesPercentage": 0.59133,
      "exchange": "NYSE",
      "source": "active"
    },
    {
      "symbol": "CIFR",
      "companyName": "Cipher Mining Inc.",
      "price": 20.42,
      "change": 1.27,
      "changesPercentage": 6.63185,
      "exchange": "NASDAQ",
      "source": "active"
    },
    {
      "symbol": "TQQQ",
      "companyName": "ProShares UltraPro QQQ",
      "price": 54.54,
      "change": 1.17,
      "changesPercentage": 2.19224,
      "exchange": "NASDAQ",
      "source": "active"
    },
    {
      "symbol": "ONMD",
      "companyName": "OneMedNet Corporation",
      "price": 1.775,
      "change": 0.355,
      "changesPercentage": 25,
      "exchange": "NASDAQ",
      "source": "active"
    },
    {
      "symbol": "ONDS",
      "companyName": "Ondas Holdings Inc.",
      "price": 7.88,
      "change": -0.36,
      "changesPercentage": -4.36893,
      "exchange": "NASDAQ",
      "source": "active"
    },
    {
      "symbol": "WULF",
      "companyName": "TeraWulf Inc.",
      "price": 15.44,
      "change": 0.6,
      "changesPercentage": 4.04313,
      "exchange": "NASDAQ",
      "source": "active"
    },
    {
      "symbol": "NIO",
      "companyName": "NIO Inc.",
      "price": 5.51,
      "change": 0.05,
      "changesPercentage": 0.91575,
      "exchange": "NYSE",
      "source": "active"
    },
    {
      "symbol": "TZA",
      "companyName": "Direxion Daily Small Cap Bear 3X Shares",
      "price": 7.405,
      "change": -0.115,
      "changesPercentage": -1.52926,
      "exchange": "AMEX",
      "source": "active"
    },
    {
      "symbol": "F",
      "companyName": "Ford Motor Company",
      "price": 13.275,
      "change": 0.085,
      "changesPercentage": 0.64443,
      "exchange": "NYSE",
      "source": "active"
    },
    {
      "symbol": "BURU",
      "companyName": "Nuburu, Inc.",
      "price": 0.2598,
      "change": 0.0394,
      "changesPercentage": 17.87659,
      "exchange": "AMEX",
      "source": "active"
    },
    {
      "symbol": "VALE",
      "companyName": "Vale S.A.",
      "price": 12.615,
      "change": 0.105,
      "changesPercentage": 0.83933,
      "exchange": "NYSE",
      "source": "active"
    },
    {
      "symbol": "SOFI",
      "companyName": "SoFi Technologies, Inc.",
      "price": 29.67,
      "change": 1.18,
      "changesPercentage": 4.1418,
      "exchange": "NASDAQ",
      "source": "active"
    },
    {
      "symbol": "BTBT",
      "companyName": "Bit Digital, Inc.",
      "price": 2.38,
      "change": 0.06,
      "changesPercentage": 2.58621,
      "exchange": "NASDAQ",
      "source": "active"
    },
    {
      "symbol": "DEFT",
      "companyName": "DeFi Technologies Inc.",
      "price": 1.52,
      "change": 0.13,
      "changesPercentage": 9.35252,
      "exchange": "NASDAQ",
      "source": "active"
    },
    {
      "symbol": "ADTX",
      "companyName": "Aditxt, Inc.",
      "price": 3.8,
      "change": 0.66,
      "changesPercentage": 21.01911,
      "exchange": "NASDAQ",
      "source": "active"
    },
    {
      "symbol": "BTG",
      "companyName": "B2Gold Corp.",
      "price": 4.62,
      "change": 0.15,
      "changesPercentage": 3.3557,
      "exchange": "AMEX",
      "source": "active"
    },
    {
      "symbol": "ACHR",
      "companyName": "Archer Aviation Inc.",
      "price": 7.79,
      "change": 0.3,
      "changesPercentage": 4.00534,
      "exchange": "NYSE",
      "source": "active"
    },
    {
      "symbol": "MARA",
      "companyName": "Marathon Digital Holdings, Inc.",
      "price": 11.81,
      "change": 0.7,
      "changesPercentage": 6.30063,
      "exchange": "NASDAQ",
      "source": "active"
    },
    {
      "symbol": "INHD",
      "companyName": "Inno Holdings Inc. Common Stock",
      "price": 0.2232,
      "change": -0.0023,
      "changesPercentage": -1.01996,
      "exchange": "NASDAQ",
      "source": "active"
    },
    {
      "symbol": "SMX",
      "companyName": "SMX (Security Matters) Public Limited Company",
      "price": 60.18,
      "change": 42.78,
      "changesPercentage": 245.86207,
      "exchange": "NASDAQ",
      "source": "gainer"
    },
    {
      "symbol": "VEEE",
      "companyName": "Twin Vee Powercats Co.",
      "price": 2.685,
      "change": 0.905,
      "changesPercentage": 50.8427,
      "exchange": "NASDAQ",
      "source": "gainer"
    },
    {
      "symbol": "WBUY",
      "companyName": "WEBUY GLOBAL Ltd. Ordinary Shares",
      "price": 2.07,
      "change": 0.57,
      "changesPercentage": 38,
      "exchange": "NASDAQ",
      "source": "gainer"
    },
    {
      "symbol": "VRCA",
      "companyName": "Verrica Pharmaceuticals Inc.",
      "price": 9.1,
      "change": 2.39,
      "changesPercentage": 35.61848,
      "exchange": "NASDAQ",
      "source": "gainer"
    },
    {
      "symbol": "CNTM",
      "companyName": "ConnectM Technology Solutions, Inc.",
      "price": 0.27,
      "change": 0.067,
      "changesPercentage": 33.00493,
      "exchange": "NASDAQ",
      "source": "gainer"
    },
    {
      "symbol": "APUS",
      "companyName": "Apimeds Pharmaceuticals US, Inc",
      "price": 2.9,
      "change": 0.71,
      "changesPercentage": 32.42009,
      "exchange": "NYSE",
      "source": "gainer"
    },
    {
      "symbol": "NWGL",
      "companyName": "Nature Wood Group Limited American Depositary Shares",
      "price": 1.41,
      "change": 0.33,
      "changesPercentage": 30.55556,
      "exchange": "NASDAQ",
      "source": "gainer"
    },
    {
      "symbol": "SRL",
      "companyName": "Scully Royalty Ltd.",
      "price": 7.06,
      "change": 1.46,
      "changesPercentage": 26.07143,
      "exchange": "NYSE",
      "source": "gainer"
    },
    {
      "symbol": "NXTT",
      "companyName": "Next Technology Holding Inc.",
      "price": 8.48,
      "change": 1.69,
      "changesPercentage": 24.88954,
      "exchange": "NASDAQ",
      "source": "gainer"
    },
    {
      "symbol": "FBYD",
      "companyName": "Falcon's Beyond Global, Inc. Class A Common Stock",
      "price": 20.42,
      "change": 3.94,
      "changesPercentage": 23.90777,
      "exchange": "NASDAQ",
      "source": "gainer"
    },
    {
      "symbol": "BNC",
      "companyName": "CEA Industries Inc. Common Stock",
      "price": 7.2,
      "change": 1.23,
      "changesPercentage": 20.60302,
      "exchange": "NASDAQ",
      "source": "gainer"
    },
    {
      "symbol": "EURKR",
      "companyName": "Eureka Acquisition Corp",
      "price": 0.48,
      "change": 0.08,
      "changesPercentage": 20,
      "exchange": "NASDAQ",
      "source": "gainer"
    },
    {
      "symbol": "PAPL",
      "companyName": "Pineapple Financial Inc.",
      "price": 3.44,
      "change": 0.56,
      "changesPercentage": 19.44444,
      "exchange": "AMEX",
      "source": "gainer"
    },
    {
      "symbol": "TMC",
      "companyName": "TMC the metals company Inc.",
      "price": 6.96,
      "change": 1.13,
      "changesPercentage": 19.3825,
      "exchange": "NASDAQ",
      "source": "gainer"
    },
    {
      "symbol": "LNZA",
      "companyName": "LanzaTech Global, Inc.",
      "price": 14.24,
      "change": 2.3,
      "changesPercentage": 19.26298,
      "exchange": "NASDAQ",
      "source": "gainer"
    },
    {
      "symbol": "GEOS",
      "companyName": "Geospace Technologies Corporation",
      "price": 13.17,
      "change": 2.05,
      "changesPercentage": 18.43525,
      "exchange": "NASDAQ",
      "source": "gainer"
    },
    {
      "symbol": "LOBO",
      "companyName": "Lobo EV Technologies Ltd.",
      "price": 0.6534,
      "change": 0.0975,
      "changesPercentage": 17.53913,
      "exchange": "NASDAQ",
      "source": "gainer"
    },
    {
      "symbol": "ONCO",
      "companyName": "Onconetix, Inc.",
      "price": 2.735,
      "change": 0.405,
      "changesPercentage": 17.38197,
      "exchange": "NASDAQ",
      "source": "gainer"
    },
    {
      "symbol": "WOK",
      "companyName": "WORK Medical Technology Group Ltd.",
      "price": 6.09,
      "change": 0.9,
      "changesPercentage": 17.34104,
      "exchange": "NASDAQ",
      "source": "gainer"
    },
    {
      "symbol": "SVRA",
      "companyName": "Savara Inc.",
      "price": 6.275,
      "change": 0.915,
      "changesPercentage": 17.0709,
      "exchange": "NASDAQ",
      "source": "gainer"
    },
    {
      "symbol": "YHC",
      "companyName": "LQR House Inc.",
      "price": 0.9836,
      "change": 0.1421,
      "changesPercentage": 16.88651,
      "exchange": "NASDAQ",
      "source": "gainer"
    },
    {
      "symbol": "JXG",
      "companyName": "JX Luxventure Limited",
      "price": 4.19,
      "change": 0.59,
      "changesPercentage": 16.38889,
      "exchange": "NASDAQ",
      "source": "gainer"
    },
    {
      "symbol": "JFBR",
      "companyName": "Jeffs' Brands Ltd",
      "price": 1.8,
      "change": 0.25,
      "changesPercentage": 16.12903,
      "exchange": "NASDAQ",
      "source": "gainer"
    },
    {
      "symbol": "OWLS",
      "companyName": "OBOOK HOLDINGS INC.",
      "price": 8.25,
      "change": 1.14,
      "changesPercentage": 16.03376,
      "exchange": "NASDAQ",
      "source": "gainer"
    },
    {
      "symbol": "ATMV",
      "companyName": "AlphaVest Acquisition Corp",
      "price": 8.7291,
      "change": 1.1991,
      "changesPercentage": 15.9243,
      "exchange": "NASDAQ",
      "source": "gainer"
    },
    {
      "symbol": "GWAV",
      "companyName": "Greenwave Technology Solutions, Inc.",
      "price": 6.64,
      "change": 0.91,
      "changesPercentage": 15.88133,
      "exchange": "NASDAQ",
      "source": "gainer"
    },
    {
      "symbol": "GFAI",
      "companyName": "Guardforce AI Co., Limited",
      "price": 0.888,
      "change": 0.118,
      "changesPercentage": 15.32468,
      "exchange": "NASDAQ",
      "source": "gainer"
    },
    {
      "symbol": "KULR",
      "companyName": "KULR Technology Group, Inc.",
      "price": 3.24,
      "change": 0.43,
      "changesPercentage": 15.30249,
      "exchange": "AMEX",
      "source": "gainer"
    },
    {
      "symbol": "YCBD",
      "companyName": "cbdMD, Inc.",
      "price": 0.618,
      "change": 0.0819,
      "changesPercentage": 15.277,
      "exchange": "AMEX",
      "source": "gainer"
    },
    {
      "symbol": "PAVS",
      "companyName": "Paranovus Entertainment Technology Ltd.",
      "price": 1.05,
      "change": 0.139,
      "changesPercentage": 15.25796,
      "exchange": "NASDAQ",
      "source": "gainer"
    },
    {
      "symbol": "ANL",
      "companyName": "Adlai Nortye Ltd.",
      "price": 1.59,
      "change": 0.21,
      "changesPercentage": 15.21739,
      "exchange": "NASDAQ",
      "source": "gainer"
    },
    {
      "symbol": "EXK",
      "companyName": "Endeavour Silver Corp.",
      "price": 9.93,
      "change": 1.31,
      "changesPercentage": 15.19722,
      "exchange": "NYSE",
      "source": "gainer"
    },
    {
      "symbol": "AREB",
      "companyName": "American Rebel Holdings, Inc.",
      "price": 1.29,
      "change": 0.17,
      "changesPercentage": 15.17857,
      "exchange": "NASDAQ",
      "source": "gainer"
    },
    {
      "symbol": "PRPH",
      "companyName": "ProPhase Labs, Inc.",
      "price": 0.2083,
      "change": 0.0273,
      "changesPercentage": 15.08287,
      "exchange": "NASDAQ",
      "source": "gainer"
    },
    {
      "symbol": "PTN",
      "companyName": "Palatin Technologies, Inc.",
      "price": 19.54,
      "change": 2.56,
      "changesPercentage": 15.07656,
      "exchange": "AMEX",
      "source": "gainer"
    },
    {
      "symbol": "COOT",
      "companyName": "Australian Oilseeds Holdings Limited Ordinary Shares",
      "price": 0.955,
      "change": 0.125,
      "changesPercentage": 15.06024,
      "exchange": "NASDAQ",
      "source": "gainer"
    },
    {
      "symbol": "SYNX",
      "companyName": "Silynxcom Ltd.",
      "price": 1.3,
      "change": 0.17,
      "changesPercentage": 15.04425,
      "exchange": "AMEX",
      "source": "gainer"
    },
    {
      "symbol": "OFAL",
      "companyName": "OFA Group",
      "price": 0.9,
      "change": 0.1174,
      "changesPercentage": 15.00128,
      "exchange": "NASDAQ",
      "source": "gainer"
    },
    {
      "symbol": "GAUZ",
      "companyName": "Gauzy Ltd. Ordinary Shares",
      "price": 2.39,
      "change": 0.31,
      "changesPercentage": 14.90385,
      "exchange": "NASDAQ",
      "source": "gainer"
    }
  ]
}